[{"tick":0,"event_type":"SPOT_CREATED","spot_id":"S_0007"},{"tick":1,"event_type":"SPOT_CREATED","spot_id":"S_0003"},{"tick":1,"event_type":"SPOT_CREATED","spot_id":"S_0008"},{"tick":1,"event_type":"SPOT_CREATED","spot_id":"S_0016"},{"tick":2,"event_type":"SPOT_CREATED","spot_id":"S_0002"},{"tick":2,"event_type":"SPOT_CREATED","spot_id":"S_0004"},{"tick":9,"event_type":"SPOT_MATCHED","spot_id":"S_0002"},{"tick":9,"event_type":"SPOT_MATCHED","spot_id":"S_0004"},{"tick":9,"event_type":"SPOT_MATCHED","spot_id":"S_0008"},{"tick":10,"event_type":"SPOT_CONFIRMED","spot_id":"S_0002"},{"tick":10,"event_type":"SPOT_MATCHED","spot_id":"S_0003"},{"tick":10,"event_type":"SPOT_CONFIRMED","spot_id":"S_0004"},{"tick":10,"event_type":"SPOT_CONFIRMED","spot_id":"S_0008"},{"tick":11,"event_type":"SPOT_STARTED","spot_id":"S_0002"},{"tick":11,"event_type":"SPOT_CONFIRMED","spot_id":"S_0003"},{"tick":11,"event_type":"SPOT_STARTED","spot_id":"S_0004"},{"tick":11,"event_type":"SPOT_MATCHED","spot_id":"S_0007"},{"tick":11,"event_type":"SPOT_STARTED","spot_id":"S_0008"},{"tick":12,"event_type":"SPOT_STARTED","spot_id":"S_0003"},{"tick":12,"event_type":"SPOT_CREATED","spot_id":"S_0005"},{"tick":12,"event_type":"SPOT_CONFIRMED","spot_id":"S_0007"},{"tick":13,"event_type":"SPOT_STARTED","spot_id":"S_0007"},{"tick":13,"event_type":"SPOT_MATCHED","spot_id":"S_0016"},{"tick":14,"event_type":"SPOT_COMPLETED","spot_id":"S_0003"},{"tick":14,"event_type":"SPOT_CREATED","spot_id":"S_0006"},{"tick":14,"event_type":"SPOT_COMPLETED","spot_id":"S_0008"},{"tick":14,"event_type":"SPOT_CREATED","spot_id":"S_0012"},{"tick":14,"event_type":"SPOT_CONFIRMED","spot_id":"S_0016"},{"tick":15,"event_type":"SPOT_COMPLETED","spot_id":"S_0002"},{"tick":15,"event_type":"SPOT_COMPLETED","spot_id":"S_0004"},{"tick":15,"event_type":"SPOT_COMPLETED","spot_id":"S_0007"},{"tick":15,"event_type":"SPOT_CREATED","spot_id":"S_0015"},{"tick":15,"event_type":"SPOT_STARTED","spot_id":"S_0016"},{"tick":19,"event_type":"SPOT_MATCHED","spot_id":"S_0005"},{"tick":19,"event_type":"SPOT_COMPLETED","spot_id":"S_0016"},{"tick":20,"event_type":"SPOT_CREATED","spot_id":"S_0001"},{"tick":20,"event_type":"SPOT_CONFIRMED","spot_id":"S_0005"},{"tick":20,"event_type":"SPOT_CREATED","spot_id":"S_0009"},{"tick":20,"event_type":"SPOT_CREATED","spot_id":"S_0017"},{"tick":21,"event_type":"SPOT_STARTED","spot_id":"S_0005"},{"tick":21,"event_type":"SPOT_MATCHED","spot_id":"S_0006"},{"tick":22,"event_type":"SPOT_CONFIRMED","spot_id":"S_0006"},{"tick":23,"event_type":"SPOT_COMPLETED","spot_id":"S_0005"},{"tick":23,"event_type":"SPOT_STARTED","spot_id":"S_0006"},{"tick":23,"event_type":"SPOT_CREATED","spot_id":"S_0014"},{"tick":26,"event_type":"SPOT_COMPLETED","spot_id":"S_0006"},{"tick":26,"event_type":"SPOT_CREATED","spot_id":"S_0011"},{"tick":26,"event_type":"SPOT_MATCHED","spot_id":"S_0012"},{"tick":26,"event_type":"SPOT_CREATED","spot_id":"S_0013"},{"tick":26,"event_type":"SPOT_MATCHED","spot_id":"S_0017"},{"tick":27,"event_type":"SPOT_CONFIRMED","spot_id":"S_0012"},{"tick":27,"event_type":"SPOT_MATCHED","spot_id":"S_0015"},{"tick":27,"event_type":"SPOT_CONFIRMED","spot_id":"S_0017"},{"tick":28,"event_type":"SPOT_STARTED","spot_id":"S_0012"},{"tick":28,"event_type":"NO_SHOW","spot_id":"S_0012","agent_id":"A_p_0081"},{"tick":28,"event_type":"SPOT_CONFIRMED","spot_id":"S_0015"},{"tick":28,"event_type":"SPOT_STARTED","spot_id":"S_0017"},{"tick":29,"event_type":"SPOT_STARTED","spot_id":"S_0015"},{"tick":30,"event_type":"SPOT_CREATED","spot_id":"S_0018"},{"tick":31,"event_type":"SPOT_COMPLETED","spot_id":"S_0017"},{"tick":32,"event_type":"SPOT_MATCHED","spot_id":"S_0001"},{"tick":32,"event_type":"SPOT_MATCHED","spot_id":"S_0009"},{"tick":32,"event_type":"SPOT_COMPLETED","spot_id":"S_0012"},{"tick":33,"event_type":"SPOT_CONFIRMED","spot_id":"S_0001"},{"tick":33,"event_type":"SPOT_CONFIRMED","spot_id":"S_0009"},{"tick":33,"event_type":"SPOT_MATCHED","spot_id":"S_0013"},{"tick":33,"event_type":"SPOT_COMPLETED","spot_id":"S_0015"},{"tick":34,"event_type":"SPOT_STARTED","spot_id":"S_0001"},{"tick":34,"event_type":"SPOT_STARTED","spot_id":"S_0009"},{"tick":34,"event_type":"SPOT_CONFIRMED","spot_id":"S_0013"},{"tick":35,"event_type":"SPOT_CREATED","spot_id":"S_0010"},{"tick":35,"event_type":"SPOT_STARTED","spot_id":"S_0013"},{"tick":35,"event_type":"NO_SHOW","spot_id":"S_0013","agent_id":"A_p_0033"},{"tick":35,"event_type":"SPOT_MATCHED","spot_id":"S_0014"},{"tick":36,"event_type":"SPOT_COMPLETED","spot_id":"S_0001"},{"tick":36,"event_type":"SPOT_COMPLETED","spot_id":"S_0009"},{"tick":36,"event_type":"SPOT_CONFIRMED","spot_id":"S_0014"},{"tick":37,"event_type":"SPOT_COMPLETED","spot_id":"S_0013"},{"tick":37,"event_type":"SPOT_STARTED","spot_id":"S_0014"},{"tick":38,"event_type":"SPOT_MATCHED","spot_id":"S_0011"},{"tick":39,"event_type":"SPOT_CONFIRMED","spot_id":"S_0011"},{"tick":40,"event_type":"SPOT_STARTED","spot_id":"S_0011"},{"tick":40,"event_type":"SPOT_MATCHED","spot_id":"S_0018"},{"tick":41,"event_type":"SPOT_COMPLETED","spot_id":"S_0014"},{"tick":41,"event_type":"SPOT_CONFIRMED","spot_id":"S_0018"},{"tick":42,"event_type":"SPOT_STARTED","spot_id":"S_0018"},{"tick":43,"event_type":"SPOT_MATCHED","spot_id":"S_0010"},{"tick":43,"event_type":"SPOT_COMPLETED","spot_id":"S_0011"},{"tick":44,"event_type":"SPOT_CONFIRMED","spot_id":"S_0010"},{"tick":45,"event_type":"SPOT_STARTED","spot_id":"S_0010"},{"tick":45,"event_type":"SPOT_COMPLETED","spot_id":"S_0018"},{"tick":47,"event_type":"SPOT_COMPLETED","spot_id":"S_0010"}]